foo.py
commentaire/__init__.py
commentaire/__main__.py
commentaire/commentaire.py
commentaire-0.0.2.dist-info/LICENSE
commentaire-0.0.2.dist-info/METADATA
commentaire-0.0.2.dist-info/WHEEL
commentaire-0.0.2.dist-info/entry_points.txt
commentaire-0.0.2.dist-info/top_level.txt
commentaire-0.0.2.dist-info/RECORD
