Metadata-Version: 2.1
Name: commentaire
Version: 0.0.2
Summary: An automatic commenter for Python code, with optional added translations.
Author-email: Emery Berger <emery.berger@gmail.com>
Project-URL: Homepage, https://github.com/emeryberger/commentaire
Project-URL: Bug Tracker, https://github.com/emeryberger/commentaire
Classifier: Programming Language :: Python :: 3
Classifier: License :: OSI Approved :: MIT License
Classifier: Operating System :: OS Independent
Requires-Python: >=3.7
License-File: LICENSE
